maccaw/__init__.py
maccaw/maccaw.py
maccaw/main.py
maccaw-0.0.1.dist-info/LICENSE
maccaw-0.0.1.dist-info/METADATA
maccaw-0.0.1.dist-info/WHEEL
maccaw-0.0.1.dist-info/top_level.txt
maccaw-0.0.1.dist-info/RECORD
